knada_kafka_consumer/__init__.py
knada_kafka_consumer/app.py
knada_kafka_consumer/bq/__init__.py
knada_kafka_consumer/bq/bigquery_writer.py
knada_kafka_consumer/consumer/__init__.py
knada_kafka_consumer/consumer/consumer.py
knada_kafka_consumer/kafka/__init__.py
knada_kafka_consumer/kafka/kafka.py
knada_kafka_consumer-0.1.11.dist-info/LICENSE
knada_kafka_consumer-0.1.11.dist-info/WHEEL
knada_kafka_consumer-0.1.11.dist-info/METADATA
knada_kafka_consumer-0.1.11.dist-info/RECORD
