Metadata-Version: 2.1
Name: knada-kafka-consumer
Version: 0.1.11
Summary: 
License: MIT
Author: NAV IT dataplattform
Requires-Python: >=3.7,<4.0
Classifier: License :: OSI Approved :: MIT License
Classifier: Programming Language :: Python :: 3
Classifier: Programming Language :: Python :: 3.7
Classifier: Programming Language :: Python :: 3.8
Classifier: Programming Language :: Python :: 3.9
Requires-Dist: avro-python3 (>=1.10.1,<2.0.0)
Requires-Dist: fastapi (>=0.61.1,<0.62.0)
Requires-Dist: fastapi-utils (>=0.2.1,<0.3.0)
Requires-Dist: google-api-core (>=1.22.2,<2.0.0)
Requires-Dist: google-auth (>=1.22.0,<2.0.0)
Requires-Dist: google-cloud (>=0.34.0,<0.35.0)
Requires-Dist: google-cloud-bigquery (>=2.1.0,<3.0.0)
Requires-Dist: google-cloud-core (>=1.4.1,<2.0.0)
Requires-Dist: google-cloud-storage (>=1.31.2,<2.0.0)
Requires-Dist: kafka-python (>=2.0.2,<3.0.0)
Requires-Dist: prometheus_client (>=0.9.0,<0.10.0)
Requires-Dist: pytest (>=6.2.1,<7.0.0)
Requires-Dist: uvicorn (>=0.12.1,<0.13.0)
